brightcove_async/__init__.py
brightcove_async/client.py
brightcove_async/exceptions.py
brightcove_async/initalise.py
brightcove_async/protocols.py
brightcove_async/py.typed
brightcove_async/registry.py
brightcove_async/settings.py
brightcove_async/oauth/__init__.py
brightcove_async/oauth/oauth.py
brightcove_async/schemas/__init__.py
brightcove_async/schemas/analytics_model.py
brightcove_async/schemas/params.py
brightcove_async/schemas/syndication_model.py
brightcove_async/schemas/cms_model/Image.py
brightcove_async/schemas/cms_model/Videofields.py
brightcove_async/schemas/cms_model/__init__.py
brightcove_async/schemas/dynamic_ingest_model/__init__.py
brightcove_async/schemas/dynamic_ingest_model/IngestMediaAssetbody/audioTracks.py
brightcove_async/services/__init__.py
brightcove_async/services/analytics.py
brightcove_async/services/base.py
brightcove_async/services/cms.py
brightcove_async/services/dynamic_ingest.py
brightcove_async/services/syndication.py
brightcove_async-0.1.8.dist-info/licenses/LICENSE.txt
brightcove_async-0.1.8.dist-info/METADATA
brightcove_async-0.1.8.dist-info/WHEEL
brightcove_async-0.1.8.dist-info/top_level.txt
brightcove_async-0.1.8.dist-info/RECORD
