Metadata-Version: 2.4
Name: brightcove_async
Version: 0.1.8
Summary: An asynchronous client for the Brightcove API.
Requires-Python: >=3.13
License-File: LICENSE.txt
Requires-Dist: aiohttp>=3.12.14
Requires-Dist: aiolimiter>=1.2.1
Requires-Dist: pydantic>=2.11.7
Requires-Dist: pydantic-settings>=2.10.1
Requires-Dist: tenacity>=9.1.2
Dynamic: license-file
